ldv/__init__.py
ldv/client.py
ldv/consts.py
ldv/utils.py
ldv/apps/__init__.py
ldv/apps/base.py
ldv/apps/presence.py
ldv/apps/rooms.py
ldvpy-0.1.dist-info/LICENSE
ldvpy-0.1.dist-info/METADATA
ldvpy-0.1.dist-info/WHEEL
ldvpy-0.1.dist-info/top_level.txt
ldvpy-0.1.dist-info/RECORD
