Metadata-Version: 2.1
Name: ldvpy
Version: 0.1
Summary: An API for the LDV dashboard
Author-email: Egsagon <egsagon12@gmail.com>
License: MIT License
Project-URL: Repository, https://github.com/Egsagon/LDVPY
Keywords: school,api,web scrapper
Classifier: Development Status :: 4 - Beta
Classifier: Programming Language :: Python
Requires-Python: >=3.11
License-File: LICENSE
Requires-Dist: requests
Requires-Dist: beautifulsoup4
Provides-Extra: cli
Requires-Dist: click ; extra == 'cli'
